prospecting/__init__.py
prospecting/api.py
prospecting/api_wip.py
prospecting/env.py
prospecting/errors.py
prospecting/utils.py
prospecting/version.py
prospecting-0.1.5.dist-info/DESCRIPTION.rst
prospecting-0.1.5.dist-info/METADATA
prospecting-0.1.5.dist-info/RECORD
prospecting-0.1.5.dist-info/WHEEL
prospecting-0.1.5.dist-info/metadata.json
prospecting-0.1.5.dist-info/top_level.txt
