Metadata-Version: 2.0
Name: prospecting
Version: 0.1.5
Summary: Marketing toolset using Pandas & Google Sheets API, with classes for a variety of other Google APIs
Home-page: https://github.com/reidbradley/prospecting
Author: Reid Bradley
Author-email: reidbradley.dev@gmail.com
License: MIT
Keywords: Pandas,Google Sheets,Google APIs
Platform: UNKNOWN
Classifier: Development Status :: 2 - Pre-Alpha
Classifier: Intended Audience :: Developers
Classifier: License :: OSI Approved :: MIT License
Classifier: Programming Language :: Python :: 3.5
Requires-Dist: google-api-python-client (>=1.5.5)
Requires-Dist: httplib2 (>=0.9.2)
Requires-Dist: numpy (>=1.11.2)
Requires-Dist: oauth2client (>=4.0.0)
Requires-Dist: pandas (>=0.18)
Requires-Dist: uritemplate (>=3.*)
